[
  {
    "date": "2026-01-01",
    "meals": [
      {
        "meal_type": "lunch",
        "time": "12:18",
        "foods": [
          "黄焖鸡米饭"
        ],
        "estimated_calories": 607,
        "tags": [
          "外卖",
          "健康"
        ]
      },
      {
        "meal_type": "dinner",
        "time": "20:57",
        "foods": [
          "零食"
        ],
        "estimated_calories": 256,
        "tags": [
          "简单",
          "凑合"
        ]
      }
    ],
    "daily_calories": 863,
    "water_ml": 997
  },
  {
    "date": "2026-01-02",
    "meals": [
      {
        "meal_type": "breakfast",
        "time": "09:04",
        "foods": [
          "咖啡",
          "面包"
        ],
        "estimated_calories": 325,
        "tags": [
          "简单",
          "便利店"
        ]
      },
      {
        "meal_type": "lunch",
        "time": "11:44",
        "foods": [
          "麻辣烫"
        ],
        "estimated_calories": 663,
        "tags": [
          "外卖",
          "健康"
        ]
      },
      {
        "meal_type": "dinner",
        "time": "21:19",
        "foods": [
          "零食"
        ],
        "estimated_calories": 287,
        "tags": [
          "简单",
          "凑合"
        ]
      }
    ],
    "daily_calories": 1275,
    "water_ml": 980
  },
  {
    "date": "2026-01-03",
    "meals": [
      {
        "meal_type": "breakfast",
        "time": "08:54",
        "foods": [
          "咖啡",
          "面包"
        ],
        "estimated_calories": 246,
        "tags": [
          "简单",
          "咖啡店"
        ]
      },
      {
        "meal_type": "lunch",
        "time": "11:47",
        "foods": [
          "黄焖鸡米饭"
        ],
        "estimated_calories": 634,
        "tags": [
          "便利店",
          "健康"
        ]
      },
      {
        "meal_type": "dinner",
        "time": "19:21",
        "foods": [
          "火锅底料",
          "蔬菜",
          "肉卷"
        ],
        "estimated_calories": 598,
        "tags": [
          "自制",
          "丰盛"
        ]
      }
    ],
    "daily_calories": 1478,
    "water_ml": 1285
  },
  {
    "date": "2026-01-04",
    "meals": [
      {
        "meal_type": "lunch",
        "time": "11:50",
        "foods": [
          "麻辣烫"
        ],
        "estimated_calories": 742,
        "tags": [
          "食堂",
          "一般"
        ]
      },
      {
        "meal_type": "dinner",
        "time": "19:17",
        "foods": [
          "煎牛排",
          "沙拉"
        ],
        "estimated_calories": 832,
        "tags": [
          "自制",
          "丰盛"
        ]
      }
    ],
    "daily_calories": 1574,
    "water_ml": 1007
  },
  {
    "date": "2026-01-05",
    "meals": [
      {
        "meal_type": "lunch",
        "time": "11:49",
        "foods": [
          "黄焖鸡米饭"
        ],
        "estimated_calories": 536,
        "tags": [
          "食堂",
          "健康"
        ]
      },
      {
        "meal_type": "dinner",
        "time": "19:16",
        "foods": [
          "烧烤",
          "啤酒"
        ],
        "estimated_calories": 677,
        "tags": [
          "自制",
          "丰盛"
        ]
      }
    ],
    "daily_calories": 1213,
    "water_ml": 1588
  },
  {
    "date": "2026-01-06",
    "meals": [
      {
        "meal_type": "lunch",
        "time": "12:12",
        "foods": [
          "麻辣烫"
        ],
        "estimated_calories": 570,
        "tags": [
          "食堂",
          "一般"
        ]
      },
      {
        "meal_type": "dinner",
        "time": "19:24",
        "foods": [
          "外卖炒菜",
          "米饭"
        ],
        "estimated_calories": 706,
        "tags": [
          "自制",
          "丰盛"
        ]
      }
    ],
    "daily_calories": 1276,
    "water_ml": 1307
  },
  {
    "date": "2026-01-07",
    "meals": [
      {
        "meal_type": "breakfast",
        "time": "08:45",
        "foods": [
          "咖啡",
          "面包"
        ],
        "estimated_calories": 192,
        "tags": [
          "简单",
          "咖啡店"
        ]
      },
      {
        "meal_type": "lunch",
        "time": "11:45",
        "foods": [
          "麻辣烫"
        ],
        "estimated_calories": 641,
        "tags": [
          "食堂",
          "一般"
        ]
      },
      {
        "meal_type": "dinner",
        "time": "20:57",
        "foods": [
          "面包",
          "牛奶"
        ],
        "estimated_calories": 380,
        "tags": [
          "简单",
          "凑合"
        ]
      }
    ],
    "daily_calories": 1213,
    "water_ml": 909
  },
  {
    "date": "2026-01-08",
    "meals": [
      {
        "meal_type": "lunch",
        "time": "12:14",
        "foods": [
          "鸡胸肉沙拉",
          "全麦面包"
        ],
        "estimated_calories": 603,
        "tags": [
          "外卖",
          "一般"
        ]
      },
      {
        "meal_type": "dinner",
        "time": "21:17",
        "foods": [
          "泡面",
          "卤蛋"
        ],
        "estimated_calories": 432,
        "tags": [
          "简单",
          "凑合"
        ]
      }
    ],
    "daily_calories": 1035,
    "water_ml": 1227
  },
  {
    "date": "2026-01-09",
    "meals": [
      {
        "meal_type": "breakfast",
        "time": "09:17",
        "foods": [
          "咖啡"
        ],
        "estimated_calories": 285,
        "tags": [
          "简单",
          "咖啡店"
        ]
      },
      {
        "meal_type": "lunch",
        "time": "12:18",
        "foods": [
          "轻食套餐"
        ],
        "estimated_calories": 746,
        "tags": [
          "外卖",
          "一般"
        ]
      },
      {
        "meal_type": "dinner",
        "time": "18:53",
        "foods": [
          "自制意面"
        ],
        "estimated_calories": 813,
        "tags": [
          "自制",
          "一般"
        ]
      }
    ],
    "daily_calories": 1844,
    "water_ml": 1103
  },
  {
    "date": "2026-01-10",
    "meals": [
      {
        "meal_type": "breakfast",
        "time": "08:37",
        "foods": [
          "酸奶",
          "麦片"
        ],
        "estimated_calories": 323,
        "tags": [
          "简单",
          "咖啡店"
        ]
      },
      {
        "meal_type": "lunch",
        "time": "12:14",
        "foods": [
          "鸡胸肉沙拉",
          "全麦面包"
        ],
        "estimated_calories": 574,
        "tags": [
          "食堂",
          "健康"
        ]
      },
      {
        "meal_type": "dinner",
        "time": "18:43",
        "foods": [
          "外卖炒菜",
          "米饭"
        ],
        "estimated_calories": 841,
        "tags": [
          "自制",
          "一般"
        ]
      }
    ],
    "daily_calories": 1738,
    "water_ml": 1543
  },
  {
    "date": "2026-01-11",
    "meals": [
      {
        "meal_type": "lunch",
        "time": "12:12",
        "foods": [
          "鸡胸肉沙拉",
          "全麦面包"
        ],
        "estimated_calories": 739,
        "tags": [
          "食堂",
          "健康"
        ]
      },
      {
        "meal_type": "dinner",
        "time": "18:30",
        "foods": [
          "煎牛排",
          "沙拉"
        ],
        "estimated_calories": 785,
        "tags": [
          "自制",
          "丰盛"
        ]
      }
    ],
    "daily_calories": 1524,
    "water_ml": 804
  },
  {
    "date": "2026-01-12",
    "meals": [
      {
        "meal_type": "lunch",
        "time": "11:51",
        "foods": [
          "轻食套餐"
        ],
        "estimated_calories": 590,
        "tags": [
          "外卖",
          "一般"
        ]
      },
      {
        "meal_type": "dinner",
        "time": "18:42",
        "foods": [
          "外卖炒菜",
          "米饭"
        ],
        "estimated_calories": 820,
        "tags": [
          "外卖",
          "丰盛"
        ]
      },
      {
        "meal_type": "night_snack",
        "time": "23:01",
        "foods": [
          "薯片",
          "可乐"
        ],
        "estimated_calories": 189,
        "tags": [
          "夜宵"
        ]
      }
    ],
    "daily_calories": 1599,
    "water_ml": 1415
  },
  {
    "date": "2026-01-13",
    "meals": [
      {
        "meal_type": "breakfast",
        "time": "09:00",
        "foods": [
          "酸奶",
          "麦片"
        ],
        "estimated_calories": 245,
        "tags": [
          "简单",
          "便利店"
        ]
      },
      {
        "meal_type": "lunch",
        "time": "12:03",
        "foods": [
          "轻食套餐"
        ],
        "estimated_calories": 728,
        "tags": [
          "外卖",
          "健康"
        ]
      },
      {
        "meal_type": "dinner",
        "time": "18:58",
        "foods": [
          "火锅底料",
          "蔬菜",
          "肉卷"
        ],
        "estimated_calories": 632,
        "tags": [
          "外卖",
          "丰盛"
        ]
      }
    ],
    "daily_calories": 1605,
    "water_ml": 804
  },
  {
    "date": "2026-01-14",
    "meals": [
      {
        "meal_type": "lunch",
        "time": "11:52",
        "foods": [
          "鸡胸肉沙拉",
          "全麦面包"
        ],
        "estimated_calories": 548,
        "tags": [
          "食堂",
          "一般"
        ]
      },
      {
        "meal_type": "dinner",
        "time": "18:56",
        "foods": [
          "烧烤",
          "啤酒"
        ],
        "estimated_calories": 566,
        "tags": [
          "外卖",
          "一般"
        ]
      }
    ],
    "daily_calories": 1114,
    "water_ml": 1567
  },
  {
    "date": "2026-01-15",
    "meals": [
      {
        "meal_type": "lunch",
        "time": "11:47",
        "foods": [
          "轻食套餐"
        ],
        "estimated_calories": 625,
        "tags": [
          "便利店",
          "健康"
        ]
      },
      {
        "meal_type": "dinner",
        "time": "21:15",
        "foods": [
          "泡面",
          "卤蛋"
        ],
        "estimated_calories": 333,
        "tags": [
          "简单",
          "凑合"
        ]
      }
    ],
    "daily_calories": 958,
    "water_ml": 1424
  },
  {
    "date": "2026-01-16",
    "meals": [
      {
        "meal_type": "breakfast",
        "time": "09:16",
        "foods": [
          "咖啡"
        ],
        "estimated_calories": 249,
        "tags": [
          "简单",
          "咖啡店"
        ]
      },
      {
        "meal_type": "lunch",
        "time": "11:47",
        "foods": [
          "鸡胸肉沙拉",
          "全麦面包"
        ],
        "estimated_calories": 702,
        "tags": [
          "外卖",
          "一般"
        ]
      },
      {
        "meal_type": "dinner",
        "time": "19:02",
        "foods": [
          "外卖炒菜",
          "米饭"
        ],
        "estimated_calories": 671,
        "tags": [
          "外卖",
          "丰盛"
        ]
      }
    ],
    "daily_calories": 1622,
    "water_ml": 1277
  },
  {
    "date": "2026-01-17",
    "meals": [
      {
        "meal_type": "breakfast",
        "time": "09:00",
        "foods": [
          "酸奶",
          "麦片"
        ],
        "estimated_calories": 222,
        "tags": [
          "简单",
          "便利店"
        ]
      },
      {
        "meal_type": "lunch",
        "time": "11:45",
        "foods": [
          "轻食套餐"
        ],
        "estimated_calories": 563,
        "tags": [
          "便利店",
          "一般"
        ]
      },
      {
        "meal_type": "dinner",
        "time": "18:41",
        "foods": [
          "自制意面"
        ],
        "estimated_calories": 693,
        "tags": [
          "外卖",
          "丰盛"
        ]
      }
    ],
    "daily_calories": 1478,
    "water_ml": 997
  },
  {
    "date": "2026-01-18",
    "meals": [
      {
        "meal_type": "lunch",
        "time": "11:52",
        "foods": [
          "轻食套餐"
        ],
        "estimated_calories": 680,
        "tags": [
          "外卖",
          "一般"
        ]
      },
      {
        "meal_type": "dinner",
        "time": "19:24",
        "foods": [
          "煎牛排",
          "沙拉"
        ],
        "estimated_calories": 626,
        "tags": [
          "外卖",
          "一般"
        ]
      },
      {
        "meal_type": "night_snack",
        "time": "22:32",
        "foods": [
          "坚果"
        ],
        "estimated_calories": 199,
        "tags": [
          "夜宵"
        ]
      }
    ],
    "daily_calories": 1505,
    "water_ml": 1543
  },
  {
    "date": "2026-01-19",
    "meals": [
      {
        "meal_type": "lunch",
        "time": "12:19",
        "foods": [
          "黄焖鸡米饭"
        ],
        "estimated_calories": 523,
        "tags": [
          "外卖",
          "健康"
        ]
      },
      {
        "meal_type": "dinner",
        "time": "18:49",
        "foods": [
          "自制意面"
        ],
        "estimated_calories": 663,
        "tags": [
          "自制",
          "丰盛"
        ]
      }
    ],
    "daily_calories": 1186,
    "water_ml": 1207
  },
  {
    "date": "2026-01-20",
    "meals": [
      {
        "meal_type": "lunch",
        "time": "11:59",
        "foods": [
          "鸡胸肉沙拉",
          "全麦面包"
        ],
        "estimated_calories": 568,
        "tags": [
          "食堂",
          "健康"
        ]
      },
      {
        "meal_type": "dinner",
        "time": "21:15",
        "foods": [
          "零食"
        ],
        "estimated_calories": 313,
        "tags": [
          "简单",
          "凑合"
        ]
      }
    ],
    "daily_calories": 881,
    "water_ml": 838
  },
  {
    "date": "2026-01-21",
    "meals": [
      {
        "meal_type": "breakfast",
        "time": "08:33",
        "foods": [
          "咖啡"
        ],
        "estimated_calories": 340,
        "tags": [
          "简单",
          "便利店"
        ]
      },
      {
        "meal_type": "lunch",
        "time": "11:53",
        "foods": [
          "麻辣烫"
        ],
        "estimated_calories": 620,
        "tags": [
          "食堂",
          "一般"
        ]
      },
      {
        "meal_type": "dinner",
        "time": "18:46",
        "foods": [
          "火锅底料",
          "蔬菜",
          "肉卷"
        ],
        "estimated_calories": 736,
        "tags": [
          "自制",
          "丰盛"
        ]
      },
      {
        "meal_type": "night_snack",
        "time": "23:12",
        "foods": [
          "薯片",
          "可乐"
        ],
        "estimated_calories": 324,
        "tags": [
          "夜宵"
        ]
      }
    ],
    "daily_calories": 2020,
    "water_ml": 1241
  },
  {
    "date": "2026-01-22",
    "meals": [
      {
        "meal_type": "lunch",
        "time": "12:01",
        "foods": [
          "麻辣烫"
        ],
        "estimated_calories": 689,
        "tags": [
          "食堂",
          "健康"
        ]
      },
      {
        "meal_type": "dinner",
        "time": "18:47",
        "foods": [
          "自制意面"
        ],
        "estimated_calories": 849,
        "tags": [
          "自制",
          "一般"
        ]
      }
    ],
    "daily_calories": 1538,
    "water_ml": 904
  },
  {
    "date": "2026-01-23",
    "meals": [
      {
        "meal_type": "lunch",
        "time": "11:47",
        "foods": [
          "鸡胸肉沙拉",
          "全麦面包"
        ],
        "estimated_calories": 650,
        "tags": [
          "便利店",
          "一般"
        ]
      },
      {
        "meal_type": "dinner",
        "time": "18:58",
        "foods": [
          "外卖炒菜",
          "米饭"
        ],
        "estimated_calories": 588,
        "tags": [
          "自制",
          "丰盛"
        ]
      }
    ],
    "daily_calories": 1238,
    "water_ml": 1591
  },
  {
    "date": "2026-01-24",
    "meals": [
      {
        "meal_type": "breakfast",
        "time": "09:16",
        "foods": [
          "咖啡",
          "面包"
        ],
        "estimated_calories": 161,
        "tags": [
          "简单",
          "咖啡店"
        ]
      },
      {
        "meal_type": "lunch",
        "time": "11:52",
        "foods": [
          "轻食套餐"
        ],
        "estimated_calories": 640,
        "tags": [
          "便利店",
          "健康"
        ]
      },
      {
        "meal_type": "dinner",
        "time": "21:18",
        "foods": [
          "面包",
          "牛奶"
        ],
        "estimated_calories": 338,
        "tags": [
          "简单",
          "凑合"
        ]
      }
    ],
    "daily_calories": 1139,
    "water_ml": 1158
  },
  {
    "date": "2026-01-25",
    "meals": [
      {
        "meal_type": "lunch",
        "time": "12:07",
        "foods": [
          "鸡胸肉沙拉",
          "全麦面包"
        ],
        "estimated_calories": 623,
        "tags": [
          "食堂",
          "一般"
        ]
      },
      {
        "meal_type": "dinner",
        "time": "18:47",
        "foods": [
          "自制意面"
        ],
        "estimated_calories": 698,
        "tags": [
          "外卖",
          "一般"
        ]
      }
    ],
    "daily_calories": 1321,
    "water_ml": 1355
  },
  {
    "date": "2026-01-26",
    "meals": [
      {
        "meal_type": "lunch",
        "time": "12:05",
        "foods": [
          "轻食套餐"
        ],
        "estimated_calories": 675,
        "tags": [
          "便利店",
          "一般"
        ]
      },
      {
        "meal_type": "dinner",
        "time": "19:18",
        "foods": [
          "煎牛排",
          "沙拉"
        ],
        "estimated_calories": 746,
        "tags": [
          "自制",
          "丰盛"
        ]
      }
    ],
    "daily_calories": 1421,
    "water_ml": 965
  },
  {
    "date": "2026-01-27",
    "meals": [
      {
        "meal_type": "breakfast",
        "time": "09:06",
        "foods": [
          "咖啡",
          "面包"
        ],
        "estimated_calories": 301,
        "tags": [
          "简单",
          "咖啡店"
        ]
      },
      {
        "meal_type": "lunch",
        "time": "12:12",
        "foods": [
          "轻食套餐"
        ],
        "estimated_calories": 628,
        "tags": [
          "便利店",
          "健康"
        ]
      },
      {
        "meal_type": "dinner",
        "time": "18:44",
        "foods": [
          "烧烤",
          "啤酒"
        ],
        "estimated_calories": 687,
        "tags": [
          "外卖",
          "一般"
        ]
      }
    ],
    "daily_calories": 1616,
    "water_ml": 1226
  },
  {
    "date": "2026-01-28",
    "meals": [
      {
        "meal_type": "breakfast",
        "time": "09:10",
        "foods": [
          "咖啡",
          "面包"
        ],
        "estimated_calories": 221,
        "tags": [
          "简单",
          "咖啡店"
        ]
      },
      {
        "meal_type": "lunch",
        "time": "11:57",
        "foods": [
          "鸡胸肉沙拉",
          "全麦面包"
        ],
        "estimated_calories": 664,
        "tags": [
          "外卖",
          "一般"
        ]
      },
      {
        "meal_type": "dinner",
        "time": "18:30",
        "foods": [
          "烧烤",
          "啤酒"
        ],
        "estimated_calories": 738,
        "tags": [
          "自制",
          "一般"
        ]
      }
    ],
    "daily_calories": 1623,
    "water_ml": 1507
  },
  {
    "date": "2026-01-29",
    "meals": [
      {
        "meal_type": "breakfast",
        "time": "08:38",
        "foods": [
          "酸奶",
          "麦片"
        ],
        "estimated_calories": 306,
        "tags": [
          "简单",
          "便利店"
        ]
      },
      {
        "meal_type": "lunch",
        "time": "12:00",
        "foods": [
          "鸡胸肉沙拉",
          "全麦面包"
        ],
        "estimated_calories": 660,
        "tags": [
          "外卖",
          "健康"
        ]
      },
      {
        "meal_type": "dinner",
        "time": "18:47",
        "foods": [
          "自制意面"
        ],
        "estimated_calories": 681,
        "tags": [
          "外卖",
          "一般"
        ]
      }
    ],
    "daily_calories": 1647,
    "water_ml": 1350
  },
  {
    "date": "2026-01-30",
    "meals": [
      {
        "meal_type": "lunch",
        "time": "11:56",
        "foods": [
          "日式便当"
        ],
        "estimated_calories": 641,
        "tags": [
          "外卖",
          "健康"
        ]
      },
      {
        "meal_type": "dinner",
        "time": "18:47",
        "foods": [
          "自制意面"
        ],
        "estimated_calories": 847,
        "tags": [
          "自制",
          "一般"
        ]
      }
    ],
    "daily_calories": 1488,
    "water_ml": 1383
  },
  {
    "date": "2026-01-31",
    "meals": [
      {
        "meal_type": "lunch",
        "time": "11:49",
        "foods": [
          "轻食套餐"
        ],
        "estimated_calories": 523,
        "tags": [
          "食堂",
          "一般"
        ]
      },
      {
        "meal_type": "dinner",
        "time": "19:22",
        "foods": [
          "自制意面"
        ],
        "estimated_calories": 646,
        "tags": [
          "自制",
          "一般"
        ]
      }
    ],
    "daily_calories": 1169,
    "water_ml": 816
  },
  {
    "date": "2026-02-01",
    "meals": [
      {
        "meal_type": "breakfast",
        "time": "08:41",
        "foods": [
          "酸奶",
          "麦片"
        ],
        "estimated_calories": 325,
        "tags": [
          "简单",
          "咖啡店"
        ]
      },
      {
        "meal_type": "lunch",
        "time": "11:44",
        "foods": [
          "黄焖鸡米饭"
        ],
        "estimated_calories": 518,
        "tags": [
          "食堂",
          "一般"
        ]
      },
      {
        "meal_type": "dinner",
        "time": "19:11",
        "foods": [
          "火锅底料",
          "蔬菜",
          "肉卷"
        ],
        "estimated_calories": 601,
        "tags": [
          "外卖",
          "一般"
        ]
      }
    ],
    "daily_calories": 1444,
    "water_ml": 1102
  },
  {
    "date": "2026-02-02",
    "meals": [
      {
        "meal_type": "breakfast",
        "time": "09:22",
        "foods": [
          "咖啡",
          "面包"
        ],
        "estimated_calories": 345,
        "tags": [
          "简单",
          "咖啡店"
        ]
      },
      {
        "meal_type": "lunch",
        "time": "11:48",
        "foods": [
          "黄焖鸡米饭"
        ],
        "estimated_calories": 697,
        "tags": [
          "外卖",
          "健康"
        ]
      },
      {
        "meal_type": "dinner",
        "time": "19:10",
        "foods": [
          "煎牛排",
          "沙拉"
        ],
        "estimated_calories": 556,
        "tags": [
          "外卖",
          "一般"
        ]
      }
    ],
    "daily_calories": 1598,
    "water_ml": 1454
  },
  {
    "date": "2026-02-03",
    "meals": [
      {
        "meal_type": "lunch",
        "time": "11:45",
        "foods": [
          "黄焖鸡米饭"
        ],
        "estimated_calories": 535,
        "tags": [
          "食堂",
          "健康"
        ]
      },
      {
        "meal_type": "dinner",
        "time": "20:49",
        "foods": [
          "零食"
        ],
        "estimated_calories": 372,
        "tags": [
          "简单",
          "凑合"
        ]
      }
    ],
    "daily_calories": 907,
    "water_ml": 844
  },
  {
    "date": "2026-02-04",
    "meals": [
      {
        "meal_type": "lunch",
        "time": "12:20",
        "foods": [
          "日式便当"
        ],
        "estimated_calories": 531,
        "tags": [
          "外卖",
          "一般"
        ]
      },
      {
        "meal_type": "dinner",
        "time": "18:48",
        "foods": [
          "外卖炒菜",
          "米饭"
        ],
        "estimated_calories": 811,
        "tags": [
          "自制",
          "一般"
        ]
      },
      {
        "meal_type": "night_snack",
        "time": "22:44",
        "foods": [
          "薯片",
          "可乐"
        ],
        "estimated_calories": 208,
        "tags": [
          "夜宵"
        ]
      }
    ],
    "daily_calories": 1550,
    "water_ml": 1141
  },
  {
    "date": "2026-02-05",
    "meals": [
      {
        "meal_type": "breakfast",
        "time": "09:11",
        "foods": [
          "酸奶",
          "麦片"
        ],
        "estimated_calories": 207,
        "tags": [
          "简单",
          "便利店"
        ]
      },
      {
        "meal_type": "lunch",
        "time": "11:47",
        "foods": [
          "轻食套餐"
        ],
        "estimated_calories": 543,
        "tags": [
          "外卖",
          "一般"
        ]
      },
      {
        "meal_type": "dinner",
        "time": "18:48",
        "foods": [
          "烧烤",
          "啤酒"
        ],
        "estimated_calories": 589,
        "tags": [
          "自制",
          "一般"
        ]
      }
    ],
    "daily_calories": 1339,
    "water_ml": 1539
  },
  {
    "date": "2026-02-06",
    "meals": [
      {
        "meal_type": "breakfast",
        "time": "08:32",
        "foods": [
          "咖啡"
        ],
        "estimated_calories": 188,
        "tags": [
          "简单",
          "咖啡店"
        ]
      },
      {
        "meal_type": "lunch",
        "time": "12:07",
        "foods": [
          "日式便当"
        ],
        "estimated_calories": 585,
        "tags": [
          "便利店",
          "一般"
        ]
      },
      {
        "meal_type": "dinner",
        "time": "18:39",
        "foods": [
          "烧烤",
          "啤酒"
        ],
        "estimated_calories": 696,
        "tags": [
          "自制",
          "一般"
        ]
      }
    ],
    "daily_calories": 1469,
    "water_ml": 1199
  },
  {
    "date": "2026-02-07",
    "meals": [
      {
        "meal_type": "breakfast",
        "time": "08:46",
        "foods": [
          "咖啡"
        ],
        "estimated_calories": 169,
        "tags": [
          "简单",
          "咖啡店"
        ]
      },
      {
        "meal_type": "lunch",
        "time": "11:49",
        "foods": [
          "黄焖鸡米饭"
        ],
        "estimated_calories": 581,
        "tags": [
          "外卖",
          "健康"
        ]
      },
      {
        "meal_type": "dinner",
        "time": "19:20",
        "foods": [
          "火锅底料",
          "蔬菜",
          "肉卷"
        ],
        "estimated_calories": 584,
        "tags": [
          "外卖",
          "丰盛"
        ]
      }
    ],
    "daily_calories": 1334,
    "water_ml": 1022
  },
  {
    "date": "2026-02-08",
    "meals": [
      {
        "meal_type": "breakfast",
        "time": "08:38",
        "foods": [
          "咖啡",
          "面包"
        ],
        "estimated_calories": 346,
        "tags": [
          "简单",
          "便利店"
        ]
      },
      {
        "meal_type": "lunch",
        "time": "12:02",
        "foods": [
          "麻辣烫"
        ],
        "estimated_calories": 626,
        "tags": [
          "食堂",
          "健康"
        ]
      },
      {
        "meal_type": "dinner",
        "time": "18:56",
        "foods": [
          "煎牛排",
          "沙拉"
        ],
        "estimated_calories": 720,
        "tags": [
          "外卖",
          "一般"
        ]
      }
    ],
    "daily_calories": 1692,
    "water_ml": 1239
  },
  {
    "date": "2026-02-09",
    "meals": [
      {
        "meal_type": "lunch",
        "time": "12:11",
        "foods": [
          "日式便当"
        ],
        "estimated_calories": 637,
        "tags": [
          "外卖",
          "健康"
        ]
      },
      {
        "meal_type": "dinner",
        "time": "19:15",
        "foods": [
          "火锅底料",
          "蔬菜",
          "肉卷"
        ],
        "estimated_calories": 819,
        "tags": [
          "外卖",
          "一般"
        ]
      }
    ],
    "daily_calories": 1456,
    "water_ml": 802
  },
  {
    "date": "2026-02-10",
    "meals": [
      {
        "meal_type": "lunch",
        "time": "11:41",
        "foods": [
          "麻辣烫"
        ],
        "estimated_calories": 642,
        "tags": [
          "食堂",
          "一般"
        ]
      },
      {
        "meal_type": "dinner",
        "time": "20:33",
        "foods": [
          "零食"
        ],
        "estimated_calories": 342,
        "tags": [
          "简单",
          "凑合"
        ]
      }
    ],
    "daily_calories": 984,
    "water_ml": 1493
  },
  {
    "date": "2026-02-11",
    "meals": [
      {
        "meal_type": "lunch",
        "time": "11:58",
        "foods": [
          "轻食套餐"
        ],
        "estimated_calories": 536,
        "tags": [
          "便利店",
          "健康"
        ]
      },
      {
        "meal_type": "dinner",
        "time": "19:22",
        "foods": [
          "自制意面"
        ],
        "estimated_calories": 578,
        "tags": [
          "外卖",
          "一般"
        ]
      }
    ],
    "daily_calories": 1114,
    "water_ml": 1363
  },
  {
    "date": "2026-02-12",
    "meals": [
      {
        "meal_type": "breakfast",
        "time": "08:31",
        "foods": [
          "咖啡"
        ],
        "estimated_calories": 258,
        "tags": [
          "简单",
          "便利店"
        ]
      },
      {
        "meal_type": "lunch",
        "time": "11:43",
        "foods": [
          "鸡胸肉沙拉",
          "全麦面包"
        ],
        "estimated_calories": 669,
        "tags": [
          "便利店",
          "一般"
        ]
      },
      {
        "meal_type": "dinner",
        "time": "19:08",
        "foods": [
          "自制意面"
        ],
        "estimated_calories": 565,
        "tags": [
          "外卖",
          "丰盛"
        ]
      },
      {
        "meal_type": "night_snack",
        "time": "22:45",
        "foods": [
          "薯片",
          "可乐"
        ],
        "estimated_calories": 153,
        "tags": [
          "夜宵"
        ]
      }
    ],
    "daily_calories": 1645,
    "water_ml": 1255
  },
  {
    "date": "2026-02-13",
    "meals": [
      {
        "meal_type": "lunch",
        "time": "11:49",
        "foods": [
          "黄焖鸡米饭"
        ],
        "estimated_calories": 620,
        "tags": [
          "便利店",
          "一般"
        ]
      },
      {
        "meal_type": "dinner",
        "time": "19:14",
        "foods": [
          "烧烤",
          "啤酒"
        ],
        "estimated_calories": 790,
        "tags": [
          "自制",
          "丰盛"
        ]
      }
    ],
    "daily_calories": 1410,
    "water_ml": 1315
  },
  {
    "date": "2026-02-14",
    "meals": [
      {
        "meal_type": "breakfast",
        "time": "08:37",
        "foods": [
          "咖啡",
          "面包"
        ],
        "estimated_calories": 165,
        "tags": [
          "简单",
          "咖啡店"
        ]
      },
      {
        "meal_type": "lunch",
        "time": "12:18",
        "foods": [
          "黄焖鸡米饭"
        ],
        "estimated_calories": 628,
        "tags": [
          "外卖",
          "一般"
        ]
      },
      {
        "meal_type": "dinner",
        "time": "18:57",
        "foods": [
          "火锅底料",
          "蔬菜",
          "肉卷"
        ],
        "estimated_calories": 833,
        "tags": [
          "自制",
          "丰盛"
        ]
      }
    ],
    "daily_calories": 1626,
    "water_ml": 1138
  },
  {
    "date": "2026-02-15",
    "meals": [
      {
        "meal_type": "breakfast",
        "time": "08:35",
        "foods": [
          "咖啡"
        ],
        "estimated_calories": 246,
        "tags": [
          "简单",
          "咖啡店"
        ]
      },
      {
        "meal_type": "lunch",
        "time": "11:53",
        "foods": [
          "轻食套餐"
        ],
        "estimated_calories": 658,
        "tags": [
          "外卖",
          "一般"
        ]
      },
      {
        "meal_type": "dinner",
        "time": "19:22",
        "foods": [
          "煎牛排",
          "沙拉"
        ],
        "estimated_calories": 589,
        "tags": [
          "自制",
          "丰盛"
        ]
      }
    ],
    "daily_calories": 1493,
    "water_ml": 1313
  },
  {
    "date": "2026-02-16",
    "meals": [
      {
        "meal_type": "lunch",
        "time": "11:50",
        "foods": [
          "鸡胸肉沙拉",
          "全麦面包"
        ],
        "estimated_calories": 705,
        "tags": [
          "食堂",
          "健康"
        ]
      },
      {
        "meal_type": "dinner",
        "time": "18:36",
        "foods": [
          "外卖炒菜",
          "米饭"
        ],
        "estimated_calories": 589,
        "tags": [
          "自制",
          "丰盛"
        ]
      },
      {
        "meal_type": "night_snack",
        "time": "22:48",
        "foods": [
          "薯片",
          "可乐"
        ],
        "estimated_calories": 288,
        "tags": [
          "夜宵"
        ]
      }
    ],
    "daily_calories": 1582,
    "water_ml": 885
  },
  {
    "date": "2026-02-17",
    "meals": [
      {
        "meal_type": "breakfast",
        "time": "08:30",
        "foods": [
          "酸奶",
          "麦片"
        ],
        "estimated_calories": 198,
        "tags": [
          "简单",
          "咖啡店"
        ]
      },
      {
        "meal_type": "lunch",
        "time": "12:20",
        "foods": [
          "鸡胸肉沙拉",
          "全麦面包"
        ],
        "estimated_calories": 561,
        "tags": [
          "食堂",
          "一般"
        ]
      },
      {
        "meal_type": "dinner",
        "time": "21:06",
        "foods": [
          "泡面",
          "卤蛋"
        ],
        "estimated_calories": 394,
        "tags": [
          "简单",
          "凑合"
        ]
      }
    ],
    "daily_calories": 1153,
    "water_ml": 1187
  },
  {
    "date": "2026-02-18",
    "meals": [
      {
        "meal_type": "breakfast",
        "time": "08:35",
        "foods": [
          "酸奶",
          "麦片"
        ],
        "estimated_calories": 152,
        "tags": [
          "简单",
          "便利店"
        ]
      },
      {
        "meal_type": "lunch",
        "time": "11:58",
        "foods": [
          "轻食套餐"
        ],
        "estimated_calories": 628,
        "tags": [
          "外卖",
          "健康"
        ]
      },
      {
        "meal_type": "dinner",
        "time": "21:16",
        "foods": [
          "零食"
        ],
        "estimated_calories": 283,
        "tags": [
          "简单",
          "凑合"
        ]
      }
    ],
    "daily_calories": 1063,
    "water_ml": 877
  },
  {
    "date": "2026-02-19",
    "meals": [
      {
        "meal_type": "lunch",
        "time": "12:12",
        "foods": [
          "鸡胸肉沙拉",
          "全麦面包"
        ],
        "estimated_calories": 628,
        "tags": [
          "外卖",
          "一般"
        ]
      },
      {
        "meal_type": "dinner",
        "time": "18:54",
        "foods": [
          "火锅底料",
          "蔬菜",
          "肉卷"
        ],
        "estimated_calories": 850,
        "tags": [
          "外卖",
          "丰盛"
        ]
      }
    ],
    "daily_calories": 1478,
    "water_ml": 1345
  },
  {
    "date": "2026-02-20",
    "meals": [
      {
        "meal_type": "breakfast",
        "time": "09:10",
        "foods": [
          "咖啡",
          "面包"
        ],
        "estimated_calories": 333,
        "tags": [
          "简单",
          "咖啡店"
        ]
      },
      {
        "meal_type": "lunch",
        "time": "11:53",
        "foods": [
          "黄焖鸡米饭"
        ],
        "estimated_calories": 696,
        "tags": [
          "便利店",
          "一般"
        ]
      },
      {
        "meal_type": "dinner",
        "time": "21:02",
        "foods": [
          "面包",
          "牛奶"
        ],
        "estimated_calories": 436,
        "tags": [
          "简单",
          "凑合"
        ]
      }
    ],
    "daily_calories": 1465,
    "water_ml": 1218
  },
  {
    "date": "2026-02-21",
    "meals": [
      {
        "meal_type": "lunch",
        "time": "12:08",
        "foods": [
          "黄焖鸡米饭"
        ],
        "estimated_calories": 586,
        "tags": [
          "食堂",
          "健康"
        ]
      },
      {
        "meal_type": "dinner",
        "time": "19:30",
        "foods": [
          "火锅底料",
          "蔬菜",
          "肉卷"
        ],
        "estimated_calories": 570,
        "tags": [
          "自制",
          "一般"
        ]
      }
    ],
    "daily_calories": 1156,
    "water_ml": 1288
  },
  {
    "date": "2026-02-22",
    "meals": [
      {
        "meal_type": "breakfast",
        "time": "08:39",
        "foods": [
          "咖啡"
        ],
        "estimated_calories": 310,
        "tags": [
          "简单",
          "便利店"
        ]
      },
      {
        "meal_type": "lunch",
        "time": "11:46",
        "foods": [
          "鸡胸肉沙拉",
          "全麦面包"
        ],
        "estimated_calories": 536,
        "tags": [
          "食堂",
          "一般"
        ]
      },
      {
        "meal_type": "dinner",
        "time": "18:59",
        "foods": [
          "烧烤",
          "啤酒"
        ],
        "estimated_calories": 636,
        "tags": [
          "自制",
          "一般"
        ]
      },
      {
        "meal_type": "night_snack",
        "time": "23:06",
        "foods": [
          "坚果"
        ],
        "estimated_calories": 240,
        "tags": [
          "夜宵"
        ]
      }
    ],
    "daily_calories": 1722,
    "water_ml": 871
  },
  {
    "date": "2026-02-23",
    "meals": [
      {
        "meal_type": "breakfast",
        "time": "09:19",
        "foods": [
          "酸奶",
          "麦片"
        ],
        "estimated_calories": 216,
        "tags": [
          "简单",
          "便利店"
        ]
      },
      {
        "meal_type": "lunch",
        "time": "11:56",
        "foods": [
          "轻食套餐"
        ],
        "estimated_calories": 666,
        "tags": [
          "外卖",
          "一般"
        ]
      },
      {
        "meal_type": "dinner",
        "time": "21:01",
        "foods": [
          "泡面",
          "卤蛋"
        ],
        "estimated_calories": 343,
        "tags": [
          "简单",
          "凑合"
        ]
      }
    ],
    "daily_calories": 1225,
    "water_ml": 1120
  },
  {
    "date": "2026-02-24",
    "meals": [
      {
        "meal_type": "lunch",
        "time": "11:48",
        "foods": [
          "轻食套餐"
        ],
        "estimated_calories": 593,
        "tags": [
          "便利店",
          "健康"
        ]
      },
      {
        "meal_type": "dinner",
        "time": "19:13",
        "foods": [
          "火锅底料",
          "蔬菜",
          "肉卷"
        ],
        "estimated_calories": 809,
        "tags": [
          "自制",
          "丰盛"
        ]
      }
    ],
    "daily_calories": 1402,
    "water_ml": 1592
  },
  {
    "date": "2026-02-25",
    "meals": [
      {
        "meal_type": "breakfast",
        "time": "09:11",
        "foods": [
          "咖啡",
          "面包"
        ],
        "estimated_calories": 339,
        "tags": [
          "简单",
          "咖啡店"
        ]
      },
      {
        "meal_type": "lunch",
        "time": "12:15",
        "foods": [
          "鸡胸肉沙拉",
          "全麦面包"
        ],
        "estimated_calories": 539,
        "tags": [
          "外卖",
          "健康"
        ]
      },
      {
        "meal_type": "dinner",
        "time": "19:06",
        "foods": [
          "火锅底料",
          "蔬菜",
          "肉卷"
        ],
        "estimated_calories": 587,
        "tags": [
          "外卖",
          "丰盛"
        ]
      }
    ],
    "daily_calories": 1465,
    "water_ml": 1335
  },
  {
    "date": "2026-02-26",
    "meals": [
      {
        "meal_type": "breakfast",
        "time": "08:59",
        "foods": [
          "咖啡"
        ],
        "estimated_calories": 286,
        "tags": [
          "简单",
          "便利店"
        ]
      },
      {
        "meal_type": "lunch",
        "time": "11:46",
        "foods": [
          "鸡胸肉沙拉",
          "全麦面包"
        ],
        "estimated_calories": 546,
        "tags": [
          "便利店",
          "一般"
        ]
      },
      {
        "meal_type": "dinner",
        "time": "21:29",
        "foods": [
          "零食"
        ],
        "estimated_calories": 446,
        "tags": [
          "简单",
          "凑合"
        ]
      }
    ],
    "daily_calories": 1278,
    "water_ml": 1121
  },
  {
    "date": "2026-02-27",
    "meals": [
      {
        "meal_type": "breakfast",
        "time": "08:51",
        "foods": [
          "咖啡"
        ],
        "estimated_calories": 274,
        "tags": [
          "简单",
          "咖啡店"
        ]
      },
      {
        "meal_type": "lunch",
        "time": "12:10",
        "foods": [
          "鸡胸肉沙拉",
          "全麦面包"
        ],
        "estimated_calories": 571,
        "tags": [
          "食堂",
          "一般"
        ]
      },
      {
        "meal_type": "dinner",
        "time": "19:30",
        "foods": [
          "火锅底料",
          "蔬菜",
          "肉卷"
        ],
        "estimated_calories": 624,
        "tags": [
          "外卖",
          "丰盛"
        ]
      }
    ],
    "daily_calories": 1469,
    "water_ml": 1590
  },
  {
    "date": "2026-02-28",
    "meals": [
      {
        "meal_type": "lunch",
        "time": "11:43",
        "foods": [
          "麻辣烫"
        ],
        "estimated_calories": 702,
        "tags": [
          "食堂",
          "健康"
        ]
      },
      {
        "meal_type": "dinner",
        "time": "18:43",
        "foods": [
          "外卖炒菜",
          "米饭"
        ],
        "estimated_calories": 766,
        "tags": [
          "自制",
          "丰盛"
        ]
      }
    ],
    "daily_calories": 1468,
    "water_ml": 866
  },
  {
    "date": "2026-03-01",
    "meals": [
      {
        "meal_type": "breakfast",
        "time": "08:55",
        "foods": [
          "咖啡",
          "面包"
        ],
        "estimated_calories": 226,
        "tags": [
          "简单",
          "便利店"
        ]
      },
      {
        "meal_type": "lunch",
        "time": "12:06",
        "foods": [
          "日式便当"
        ],
        "estimated_calories": 554,
        "tags": [
          "便利店",
          "健康"
        ]
      },
      {
        "meal_type": "dinner",
        "time": "18:33",
        "foods": [
          "外卖炒菜",
          "米饭"
        ],
        "estimated_calories": 769,
        "tags": [
          "自制",
          "丰盛"
        ]
      }
    ],
    "daily_calories": 1549,
    "water_ml": 1079
  },
  {
    "date": "2026-03-02",
    "meals": [
      {
        "meal_type": "lunch",
        "time": "12:10",
        "foods": [
          "日式便当"
        ],
        "estimated_calories": 676,
        "tags": [
          "外卖",
          "健康"
        ]
      },
      {
        "meal_type": "dinner",
        "time": "19:14",
        "foods": [
          "煎牛排",
          "沙拉"
        ],
        "estimated_calories": 749,
        "tags": [
          "外卖",
          "一般"
        ]
      },
      {
        "meal_type": "night_snack",
        "time": "23:12",
        "foods": [
          "泡面"
        ],
        "estimated_calories": 307,
        "tags": [
          "夜宵"
        ]
      }
    ],
    "daily_calories": 1732,
    "water_ml": 915
  },
  {
    "date": "2026-03-03",
    "meals": [
      {
        "meal_type": "lunch",
        "time": "12:00",
        "foods": [
          "鸡胸肉沙拉",
          "全麦面包"
        ],
        "estimated_calories": 538,
        "tags": [
          "食堂",
          "一般"
        ]
      },
      {
        "meal_type": "dinner",
        "time": "18:50",
        "foods": [
          "外卖炒菜",
          "米饭"
        ],
        "estimated_calories": 758,
        "tags": [
          "自制",
          "一般"
        ]
      }
    ],
    "daily_calories": 1296,
    "water_ml": 1554
  },
  {
    "date": "2026-03-04",
    "meals": [
      {
        "meal_type": "lunch",
        "time": "12:20",
        "foods": [
          "轻食套餐"
        ],
        "estimated_calories": 663,
        "tags": [
          "便利店",
          "一般"
        ]
      },
      {
        "meal_type": "dinner",
        "time": "19:17",
        "foods": [
          "自制意面"
        ],
        "estimated_calories": 765,
        "tags": [
          "外卖",
          "丰盛"
        ]
      }
    ],
    "daily_calories": 1428,
    "water_ml": 967
  },
  {
    "date": "2026-03-05",
    "meals": [
      {
        "meal_type": "breakfast",
        "time": "09:13",
        "foods": [
          "咖啡"
        ],
        "estimated_calories": 153,
        "tags": [
          "简单",
          "便利店"
        ]
      },
      {
        "meal_type": "lunch",
        "time": "12:03",
        "foods": [
          "鸡胸肉沙拉",
          "全麦面包"
        ],
        "estimated_calories": 577,
        "tags": [
          "食堂",
          "一般"
        ]
      },
      {
        "meal_type": "dinner",
        "time": "19:11",
        "foods": [
          "火锅底料",
          "蔬菜",
          "肉卷"
        ],
        "estimated_calories": 761,
        "tags": [
          "自制",
          "丰盛"
        ]
      }
    ],
    "daily_calories": 1491,
    "water_ml": 1233
  },
  {
    "date": "2026-03-06",
    "meals": [
      {
        "meal_type": "lunch",
        "time": "12:01",
        "foods": [
          "鸡胸肉沙拉",
          "全麦面包"
        ],
        "estimated_calories": 737,
        "tags": [
          "外卖",
          "健康"
        ]
      },
      {
        "meal_type": "dinner",
        "time": "18:41",
        "foods": [
          "煎牛排",
          "沙拉"
        ],
        "estimated_calories": 633,
        "tags": [
          "自制",
          "丰盛"
        ]
      }
    ],
    "daily_calories": 1370,
    "water_ml": 1327
  },
  {
    "date": "2026-03-07",
    "meals": [
      {
        "meal_type": "lunch",
        "time": "12:20",
        "foods": [
          "麻辣烫"
        ],
        "estimated_calories": 679,
        "tags": [
          "便利店",
          "一般"
        ]
      },
      {
        "meal_type": "dinner",
        "time": "21:21",
        "foods": [
          "泡面",
          "卤蛋"
        ],
        "estimated_calories": 272,
        "tags": [
          "简单",
          "凑合"
        ]
      }
    ],
    "daily_calories": 951,
    "water_ml": 1293
  },
  {
    "date": "2026-03-08",
    "meals": [
      {
        "meal_type": "lunch",
        "time": "12:11",
        "foods": [
          "日式便当"
        ],
        "estimated_calories": 737,
        "tags": [
          "便利店",
          "一般"
        ]
      },
      {
        "meal_type": "dinner",
        "time": "19:02",
        "foods": [
          "煎牛排",
          "沙拉"
        ],
        "estimated_calories": 566,
        "tags": [
          "自制",
          "丰盛"
        ]
      }
    ],
    "daily_calories": 1303,
    "water_ml": 1421
  },
  {
    "date": "2026-03-09",
    "meals": [
      {
        "meal_type": "lunch",
        "time": "11:47",
        "foods": [
          "黄焖鸡米饭"
        ],
        "estimated_calories": 719,
        "tags": [
          "食堂",
          "一般"
        ]
      },
      {
        "meal_type": "dinner",
        "time": "19:20",
        "foods": [
          "火锅底料",
          "蔬菜",
          "肉卷"
        ],
        "estimated_calories": 761,
        "tags": [
          "自制",
          "一般"
        ]
      }
    ],
    "daily_calories": 1480,
    "water_ml": 1425
  },
  {
    "date": "2026-03-10",
    "meals": [
      {
        "meal_type": "lunch",
        "time": "11:57",
        "foods": [
          "麻辣烫"
        ],
        "estimated_calories": 578,
        "tags": [
          "食堂",
          "一般"
        ]
      },
      {
        "meal_type": "dinner",
        "time": "19:28",
        "foods": [
          "火锅底料",
          "蔬菜",
          "肉卷"
        ],
        "estimated_calories": 566,
        "tags": [
          "外卖",
          "一般"
        ]
      }
    ],
    "daily_calories": 1144,
    "water_ml": 1099
  },
  {
    "date": "2026-03-11",
    "meals": [
      {
        "meal_type": "lunch",
        "time": "12:18",
        "foods": [
          "麻辣烫"
        ],
        "estimated_calories": 585,
        "tags": [
          "外卖",
          "健康"
        ]
      },
      {
        "meal_type": "dinner",
        "time": "18:55",
        "foods": [
          "自制意面"
        ],
        "estimated_calories": 751,
        "tags": [
          "外卖",
          "丰盛"
        ]
      },
      {
        "meal_type": "night_snack",
        "time": "23:10",
        "foods": [
          "坚果"
        ],
        "estimated_calories": 336,
        "tags": [
          "夜宵"
        ]
      }
    ],
    "daily_calories": 1672,
    "water_ml": 938
  },
  {
    "date": "2026-03-12",
    "meals": [
      {
        "meal_type": "dinner",
        "time": "20:06",
        "foods": [
          "啤酒",
          "花生米"
        ],
        "estimated_calories": 623,
        "tags": [
          "不健康",
          "情绪化"
        ]
      }
    ],
    "daily_calories": 623,
    "water_ml": 492
  },
  {
    "date": "2026-03-13",
    "meals": [
      {
        "meal_type": "dinner",
        "time": "19:16",
        "foods": [
          "薯片",
          "酒"
        ],
        "estimated_calories": 460,
        "tags": [
          "不健康",
          "情绪化"
        ]
      }
    ],
    "daily_calories": 460,
    "water_ml": 652
  },
  {
    "date": "2026-03-14",
    "meals": [],
    "daily_calories": 0,
    "water_ml": 737
  },
  {
    "date": "2026-03-15",
    "meals": [],
    "daily_calories": 0,
    "water_ml": 504
  },
  {
    "date": "2026-03-16",
    "meals": [],
    "daily_calories": 0,
    "water_ml": 779
  },
  {
    "date": "2026-03-17",
    "meals": [
      {
        "meal_type": "breakfast",
        "time": "08:35",
        "foods": [
          "咖啡",
          "面包"
        ],
        "estimated_calories": 261,
        "tags": [
          "简单",
          "咖啡店"
        ]
      },
      {
        "meal_type": "lunch",
        "time": "12:20",
        "foods": [
          "日式便当"
        ],
        "estimated_calories": 539,
        "tags": [
          "外卖",
          "一般"
        ]
      },
      {
        "meal_type": "dinner",
        "time": "18:31",
        "foods": [
          "自制意面"
        ],
        "estimated_calories": 782,
        "tags": [
          "自制",
          "一般"
        ]
      }
    ],
    "daily_calories": 1582,
    "water_ml": 1428
  },
  {
    "date": "2026-03-18",
    "meals": [
      {
        "meal_type": "breakfast",
        "time": "09:04",
        "foods": [
          "咖啡",
          "面包"
        ],
        "estimated_calories": 335,
        "tags": [
          "简单",
          "便利店"
        ]
      },
      {
        "meal_type": "lunch",
        "time": "11:56",
        "foods": [
          "鸡胸肉沙拉",
          "全麦面包"
        ],
        "estimated_calories": 570,
        "tags": [
          "外卖",
          "一般"
        ]
      },
      {
        "meal_type": "dinner",
        "time": "19:10",
        "foods": [
          "煎牛排",
          "沙拉"
        ],
        "estimated_calories": 602,
        "tags": [
          "外卖",
          "丰盛"
        ]
      }
    ],
    "daily_calories": 1507,
    "water_ml": 885
  },
  {
    "date": "2026-03-19",
    "meals": [
      {
        "meal_type": "breakfast",
        "time": "08:46",
        "foods": [
          "咖啡",
          "面包"
        ],
        "estimated_calories": 173,
        "tags": [
          "简单",
          "咖啡店"
        ]
      },
      {
        "meal_type": "lunch",
        "time": "12:11",
        "foods": [
          "麻辣烫"
        ],
        "estimated_calories": 733,
        "tags": [
          "外卖",
          "健康"
        ]
      },
      {
        "meal_type": "dinner",
        "time": "19:20",
        "foods": [
          "外卖炒菜",
          "米饭"
        ],
        "estimated_calories": 761,
        "tags": [
          "外卖",
          "丰盛"
        ]
      }
    ],
    "daily_calories": 1667,
    "water_ml": 853
  },
  {
    "date": "2026-03-20",
    "meals": [
      {
        "meal_type": "lunch",
        "time": "12:04",
        "foods": [
          "麻辣烫"
        ],
        "estimated_calories": 662,
        "tags": [
          "食堂",
          "一般"
        ]
      },
      {
        "meal_type": "dinner",
        "time": "18:30",
        "foods": [
          "自制意面"
        ],
        "estimated_calories": 840,
        "tags": [
          "外卖",
          "一般"
        ]
      }
    ],
    "daily_calories": 1502,
    "water_ml": 1495
  },
  {
    "date": "2026-03-21",
    "meals": [
      {
        "meal_type": "lunch",
        "time": "12:19",
        "foods": [
          "日式便当"
        ],
        "estimated_calories": 639,
        "tags": [
          "外卖",
          "一般"
        ]
      },
      {
        "meal_type": "dinner",
        "time": "18:46",
        "foods": [
          "外卖炒菜",
          "米饭"
        ],
        "estimated_calories": 648,
        "tags": [
          "外卖",
          "一般"
        ]
      }
    ],
    "daily_calories": 1287,
    "water_ml": 1332
  },
  {
    "date": "2026-03-22",
    "meals": [
      {
        "meal_type": "breakfast",
        "time": "08:53",
        "foods": [
          "咖啡",
          "面包"
        ],
        "estimated_calories": 205,
        "tags": [
          "简单",
          "咖啡店"
        ]
      },
      {
        "meal_type": "lunch",
        "time": "12:00",
        "foods": [
          "黄焖鸡米饭"
        ],
        "estimated_calories": 556,
        "tags": [
          "外卖",
          "一般"
        ]
      },
      {
        "meal_type": "dinner",
        "time": "19:00",
        "foods": [
          "自制意面"
        ],
        "estimated_calories": 597,
        "tags": [
          "自制",
          "丰盛"
        ]
      }
    ],
    "daily_calories": 1358,
    "water_ml": 1366
  },
  {
    "date": "2026-03-23",
    "meals": [
      {
        "meal_type": "lunch",
        "time": "12:05",
        "foods": [
          "黄焖鸡米饭"
        ],
        "estimated_calories": 564,
        "tags": [
          "外卖",
          "一般"
        ]
      },
      {
        "meal_type": "dinner",
        "time": "19:26",
        "foods": [
          "烧烤",
          "啤酒"
        ],
        "estimated_calories": 751,
        "tags": [
          "外卖",
          "丰盛"
        ]
      }
    ],
    "daily_calories": 1315,
    "water_ml": 944
  },
  {
    "date": "2026-03-24",
    "meals": [
      {
        "meal_type": "lunch",
        "time": "12:07",
        "foods": [
          "轻食套餐"
        ],
        "estimated_calories": 608,
        "tags": [
          "便利店",
          "健康"
        ]
      },
      {
        "meal_type": "dinner",
        "time": "21:09",
        "foods": [
          "泡面",
          "卤蛋"
        ],
        "estimated_calories": 405,
        "tags": [
          "简单",
          "凑合"
        ]
      }
    ],
    "daily_calories": 1013,
    "water_ml": 939
  },
  {
    "date": "2026-03-25",
    "meals": [
      {
        "meal_type": "breakfast",
        "time": "09:27",
        "foods": [
          "咖啡"
        ],
        "estimated_calories": 166,
        "tags": [
          "简单",
          "便利店"
        ]
      },
      {
        "meal_type": "lunch",
        "time": "11:50",
        "foods": [
          "鸡胸肉沙拉",
          "全麦面包"
        ],
        "estimated_calories": 745,
        "tags": [
          "便利店",
          "健康"
        ]
      },
      {
        "meal_type": "dinner",
        "time": "18:48",
        "foods": [
          "煎牛排",
          "沙拉"
        ],
        "estimated_calories": 821,
        "tags": [
          "自制",
          "丰盛"
        ]
      },
      {
        "meal_type": "night_snack",
        "time": "22:41",
        "foods": [
          "坚果"
        ],
        "estimated_calories": 259,
        "tags": [
          "夜宵"
        ]
      }
    ],
    "daily_calories": 1991,
    "water_ml": 1353
  },
  {
    "date": "2026-03-26",
    "meals": [
      {
        "meal_type": "breakfast",
        "time": "08:34",
        "foods": [
          "咖啡",
          "面包"
        ],
        "estimated_calories": 318,
        "tags": [
          "简单",
          "便利店"
        ]
      },
      {
        "meal_type": "lunch",
        "time": "12:03",
        "foods": [
          "黄焖鸡米饭"
        ],
        "estimated_calories": 699,
        "tags": [
          "食堂",
          "一般"
        ]
      },
      {
        "meal_type": "dinner",
        "time": "19:14",
        "foods": [
          "外卖炒菜",
          "米饭"
        ],
        "estimated_calories": 718,
        "tags": [
          "外卖",
          "丰盛"
        ]
      }
    ],
    "daily_calories": 1735,
    "water_ml": 1025
  },
  {
    "date": "2026-03-27",
    "meals": [
      {
        "meal_type": "breakfast",
        "time": "08:34",
        "foods": [
          "酸奶",
          "麦片"
        ],
        "estimated_calories": 222,
        "tags": [
          "简单",
          "咖啡店"
        ]
      },
      {
        "meal_type": "lunch",
        "time": "12:13",
        "foods": [
          "黄焖鸡米饭"
        ],
        "estimated_calories": 526,
        "tags": [
          "便利店",
          "健康"
        ]
      },
      {
        "meal_type": "dinner",
        "time": "19:30",
        "foods": [
          "外卖炒菜",
          "米饭"
        ],
        "estimated_calories": 843,
        "tags": [
          "自制",
          "丰盛"
        ]
      }
    ],
    "daily_calories": 1591,
    "water_ml": 1024
  },
  {
    "date": "2026-03-28",
    "meals": [
      {
        "meal_type": "breakfast",
        "time": "09:21",
        "foods": [
          "酸奶",
          "麦片"
        ],
        "estimated_calories": 277,
        "tags": [
          "简单",
          "咖啡店"
        ]
      },
      {
        "meal_type": "lunch",
        "time": "11:57",
        "foods": [
          "轻食套餐"
        ],
        "estimated_calories": 530,
        "tags": [
          "外卖",
          "健康"
        ]
      },
      {
        "meal_type": "dinner",
        "time": "18:50",
        "foods": [
          "煎牛排",
          "沙拉"
        ],
        "estimated_calories": 746,
        "tags": [
          "外卖",
          "一般"
        ]
      }
    ],
    "daily_calories": 1553,
    "water_ml": 1250
  },
  {
    "date": "2026-03-29",
    "meals": [
      {
        "meal_type": "lunch",
        "time": "11:40",
        "foods": [
          "轻食套餐"
        ],
        "estimated_calories": 572,
        "tags": [
          "外卖",
          "健康"
        ]
      },
      {
        "meal_type": "dinner",
        "time": "19:04",
        "foods": [
          "煎牛排",
          "沙拉"
        ],
        "estimated_calories": 570,
        "tags": [
          "自制",
          "一般"
        ]
      },
      {
        "meal_type": "night_snack",
        "time": "22:36",
        "foods": [
          "坚果"
        ],
        "estimated_calories": 335,
        "tags": [
          "夜宵"
        ]
      }
    ],
    "daily_calories": 1477,
    "water_ml": 1010
  },
  {
    "date": "2026-03-30",
    "meals": [
      {
        "meal_type": "breakfast",
        "time": "08:52",
        "foods": [
          "酸奶",
          "麦片"
        ],
        "estimated_calories": 170,
        "tags": [
          "简单",
          "便利店"
        ]
      },
      {
        "meal_type": "lunch",
        "time": "12:11",
        "foods": [
          "日式便当"
        ],
        "estimated_calories": 512,
        "tags": [
          "食堂",
          "健康"
        ]
      },
      {
        "meal_type": "dinner",
        "time": "18:59",
        "foods": [
          "火锅底料",
          "蔬菜",
          "肉卷"
        ],
        "estimated_calories": 612,
        "tags": [
          "自制",
          "一般"
        ]
      },
      {
        "meal_type": "night_snack",
        "time": "22:33",
        "foods": [
          "薯片",
          "可乐"
        ],
        "estimated_calories": 185,
        "tags": [
          "夜宵"
        ]
      }
    ],
    "daily_calories": 1479,
    "water_ml": 873
  },
  {
    "date": "2026-03-31",
    "meals": [
      {
        "meal_type": "breakfast",
        "time": "09:14",
        "foods": [
          "咖啡"
        ],
        "estimated_calories": 261,
        "tags": [
          "简单",
          "咖啡店"
        ]
      },
      {
        "meal_type": "lunch",
        "time": "11:50",
        "foods": [
          "鸡胸肉沙拉",
          "全麦面包"
        ],
        "estimated_calories": 548,
        "tags": [
          "便利店",
          "健康"
        ]
      },
      {
        "meal_type": "dinner",
        "time": "21:04",
        "foods": [
          "泡面",
          "卤蛋"
        ],
        "estimated_calories": 426,
        "tags": [
          "简单",
          "凑合"
        ]
      }
    ],
    "daily_calories": 1235,
    "water_ml": 981
  }
]